domjudge_utility/__init__.py
domjudge_utility/dump.py
domjudge_utility/dump_config.py
domjudge_utility/utils.py
domjudge_utility/version.py
domjudge_utility-0.0.23.dist-info/LICENSE
domjudge_utility-0.0.23.dist-info/METADATA
domjudge_utility-0.0.23.dist-info/WHEEL
domjudge_utility-0.0.23.dist-info/RECORD
